emojineer
