Metadata-Version: 2.1
Name: emojineer
Version: 0.1.9
Summary: emojineer for emojineering
Home-page: https://github.com/kzkzgit/emojineer
Author: kzkz potato
Author-email: kzkz.ozn@gmail.com
License: UNKNOWN
Platform: UNKNOWN
Classifier: Programming Language :: Python :: 3
Classifier: License :: OSI Approved :: MIT License
Classifier: Operating System :: OS Independent
Requires-Dist: numpy (==1.14.5)
Requires-Dist: opencv-python (==3.4.2.17)
Requires-Dist: Pillow (==5.2.0)
